README.md
setup.py
tcnlu/__init__.py
tcnlu/alexa.py
tcnlu/dialogflow.py
tcnlu/exceptions.py
tcnlu/formats.py
tcnlu/humans.py
tcnlu/main.py
tcnlu/objects.py
tcnlu/rasa.py
tcnlu/tools.py
tcnlu.egg-info/PKG-INFO
tcnlu.egg-info/SOURCES.txt
tcnlu.egg-info/dependency_links.txt
tcnlu.egg-info/entry_points.txt
tcnlu.egg-info/not-zip-safe
tcnlu.egg-info/requires.txt
tcnlu.egg-info/top_level.txt