Metadata-Version: 1.0
Name: tcnlu
Version: 0.1
Summary: Format manipulations for NLU platforms
Home-page: http://github.com/pmelet/tcnlu
Author: pmelet
Author-email: melet.pierre.etienne@gmail.com
License: MIT
Platform: UNKNOWN
